vintasend_sqlalchemy/__init__.py
vintasend_sqlalchemy/alembic_initial_migration_ops.py
vintasend_sqlalchemy/model_factory.py
vintasend_sqlalchemy/py.typed
vintasend_sqlalchemy/services/__init__.py
vintasend_sqlalchemy/services/notification_backends/__init__.py
vintasend_sqlalchemy/services/notification_backends/sqlalchemy_notification_backend.py
vintasend_sqlalchemy/services/tests/__init__.py
vintasend_sqlalchemy/services/tests/test_sqlalchemy_asyncio_notification_backend.py
vintasend_sqlalchemy/services/tests/test_sqlalchemy_notification_backend.py
vintasend_sqlalchemy-0.1.4.dist-info/LICENSE.txt
vintasend_sqlalchemy-0.1.4.dist-info/METADATA
vintasend_sqlalchemy-0.1.4.dist-info/WHEEL
vintasend_sqlalchemy-0.1.4.dist-info/RECORD
